AUTHORS.rst
CONTRIBUTING.rst
HISTORY.rst
LICENSE
MANIFEST.in
README.rst
requirements.txt
setup.cfg
setup.py
docs/Makefile
docs/authors.rst
docs/conf.py
docs/contributing.rst
docs/history.rst
docs/index.rst
docs/installation.rst
docs/make.bat
docs/readme.rst
docs/usage.rst
slinky/__init__.py
slinky/slinky.py
slinky.egg-info/PKG-INFO
slinky.egg-info/SOURCES.txt
slinky.egg-info/dependency_links.txt
slinky.egg-info/entry_points.txt
slinky.egg-info/not-zip-safe
slinky.egg-info/requires.txt
slinky.egg-info/top_level.txt
tests/__init__.py
tests/test_slinky.py