Metadata-Version: 1.1
Name: slinky
Version: 0.1.2
Summary: Quick command to create signed links on S3
Home-page: https://github.com/bwghughes/slinky
Author: Ben Hughes
Author-email: bwghughes@gmail.com
License: BSD
Keywords: slinky
Platform: UNKNOWN
Classifier: Development Status :: 2 - Pre-Alpha
Classifier: Intended Audience :: Developers
Classifier: License :: OSI Approved :: BSD License
Classifier: Natural Language :: English
Classifier: Programming Language :: Python :: 2
Classifier: Programming Language :: Python :: 2.6
Classifier: Programming Language :: Python :: 2.7
Classifier: Programming Language :: Python :: 3
Classifier: Programming Language :: Python :: 3.3
Classifier: Programming Language :: Python :: 3.4
